RandomPokemon/RamdomPokemon.py
RandomPokemon/__init__.py
RandomPokemon-1.0.0.dist-info/METADATA
RandomPokemon-1.0.0.dist-info/WHEEL
RandomPokemon-1.0.0.dist-info/top_level.txt
RandomPokemon-1.0.0.dist-info/RECORD
