Metadata-Version: 2.1
Name: RandomPokemon
Version: 1.0.0
Summary: Una biblioteca que contiene la clase RandomPokemon
Author: Martha Morales
Author-email: tu@email.com
Requires-Dist: pandas
